{
    "visual": {
        "name": "Drill_Down_Pie_PIN_by_ZoomCharts",
        "displayName": "Drill Down Pie PRO (PIN) by ZoomCharts",
        "guid": "ZoomChartsDrillDownPiePin44BB3B013FB049ABB7E8DDAA6A478B1B",
        "visualClassName": "PiePin",
        "version": "1.12.16.0",
        "description": "Drill Down Pie PRO (Pin) Visual",
        "supportUrl": "https://zoomcharts.com/en/microsoft-power-bi-custom-visuals/help-center/contact-support/",
        "gitHubUrl": ""
    },
    "author": {
        "name": "ZoomCharts",
        "email": "powerbi@zoomcharts.com"
    },
    "apiVersion": "5.9.0",
    "style": "style/visual.less",
    "stringResources": {},
    "capabilities": {
        "dataRoles": [
            {
                "displayName": "Category",
                "name": "Category",
                "kind": "Grouping"
            },
            {
                "displayName": "Values",
                "name": "Values",
                "kind": "Measure"
            },
            {
                "displayName": "Slice Image",
                "description": "The field for slice images. Only base64 encoded image content is displayed (URI that starts with data:image/<format>;base64).",
                "name": "sliceImage",
                "kind": "Measure"
            },
            {
                "displayName": "Tooltip Content",
                "name": "tooltipContent",
                "kind": "Measure"
            }
        ],
        "sorting": {
            "default": {}
        },
        "supportsHighlight": false,
        "supportsLandingPage": true,
        "supportsKeyboardFocus": false,
        "supportsMultiVisualSelection": true,
        "tooltips": {
            "supportedTypes": {
                "default": true,
                "canvas": true
            }
        },
        "privileges": [],
        "dataViewMappings": [
            {
                "conditions": [
                    {
                        "Category": {
                            "min": 0,
                            "max": 9
                        },
                        "Values": {
                            "min": 0,
                            "max": 1
                        },
                        "sliceImage": {
                            "min": 0,
                            "max": 1
                        },
                        "tooltipContent": {
                            "min": 0
                        }
                    }
                ],
                "matrix": {
                    "rows": {
                        "for": {
                            "in": "Category"
                        },
                        "dataReductionAlgorithm": {
                            "top": {
                                "count": 100000
                            }
                        }
                    },
                    "columns": {
                        "for": {
                            "in": ""
                        }
                    },
                    "values": {
                        "select": [
                            {
                                "for": {
                                    "in": "Values"
                                }
                            },
                            {
                                "for": {
                                    "in": "sliceImage"
                                }
                            },
                            {
                                "for": {
                                    "in": "tooltipContent"
                                }
                            }
                        ]
                    }
                }
            }
        ],
        "subtotals": {
            "matrix": {
                "rowSubtotals": {
                    "propertyIdentifier": {
                        "objectName": "subTotals",
                        "propertyName": "rowSubtotals"
                    },
                    "defaultValue": true
                },
                "rowSubtotalsPerLevel": {
                    "propertyIdentifier": {
                        "objectName": "subTotals",
                        "propertyName": "perRowLevel"
                    },
                    "defaultValue": false
                },
                "columnSubtotals": {
                    "propertyIdentifier": {
                        "objectName": "subTotals",
                        "propertyName": "columnSubtotals"
                    },
                    "defaultValue": true
                },
                "columnSubtotalsPerLevel": {
                    "propertyIdentifier": {
                        "objectName": "subTotals",
                        "propertyName": "perColumnLevel"
                    },
                    "defaultValue": false
                },
                "levelSubtotalEnabled": {
                    "propertyIdentifier": {
                        "objectName": "subTotals",
                        "propertyName": "levelSubtotalEnabled"
                    },
                    "defaultValue": true
                }
            }
        },
        "objects": {
            "general": {
                "displayName": "General",
                "properties": {
                    "formatString": {
                        "type": {
                            "formatting": {
                                "formatString": true
                            }
                        }
                    }
                }
            },
            "paid": {
                "displayName": "Paid Features",
                "properties": {
                    "show": {
                        "displayName": "Show",
                        "type": {
                            "bool": true
                        }
                    }
                }
            },
            "trialLicense": {
                "displayName": "Trial License",
                "description": "Currently, this block is meant to be hidden.",
                "properties": {
                    "trialAccessStartDate": {
                        "displayName": "Trial Access Start Date",
                        "type": {
                            "numeric": true
                        }
                    },
                    "validLicenseProvided": {
                        "displayName": "Valid License Provided",
                        "type": {
                            "bool": true
                        }
                    }
                }
            },
            "license": {
                "displayName": "License Settings",
                "properties": {
                    "key": {
                        "displayName": "License Key",
                        "type": {
                            "text": true
                        }
                    },
                    "hash": {
                        "displayName": "License Hash",
                        "type": {
                            "text": true
                        }
                    },
                    "info": {
                        "displayName": "Info button",
                        "description": "Turn off to hide the info button. The info button can only be removed if a paid license is detected.",
                        "type": {
                            "bool": true
                        }
                    }
                }
            },
            "advanced": {
                "displayName": "Advanced Settings",
                "properties": {
                    "preview": {
                        "displayName": "Preview Features",
                        "description": "Hidden field, only enabling it from a theme to allow some functionallity.",
                        "type": {
                            "bool": true
                        }
                    },
                    "hideProperties": {
                        "displayName": "Hide Properties",
                        "description": "Hidden field, provide values delimited with ',' from a theme to hide properties.",
                        "type": {
                            "text": true
                        }
                    },
                    "responsiveFonts": {
                        "displayName": "Responsive Font Size",
                        "type": {
                            "enumeration": [
                                {
                                    "value": "off",
                                    "displayName": "Off"
                                },
                                {
                                    "value": "on",
                                    "displayName": "On"
                                }
                            ]
                        }
                    },
                    "fontSizeUnit": {
                        "displayName": "Font Size Unit",
                        "type": {
                            "enumeration": [
                                {
                                    "value": "px",
                                    "displayName": "px"
                                },
                                {
                                    "value": "pt",
                                    "displayName": "pt"
                                }
                            ]
                        }
                    }
                }
            },
            "filterSettings": {
                "displayName": "Use As Filter",
                "properties": {
                    "show": {
                        "displayName": "Show",
                        "type": {
                            "bool": true
                        }
                    }
                }
            },
            "donut": {
                "displayName": "Pie",
                "properties": {
                    "radius": {
                        "displayName": "Outer Radius",
                        "description": "The outer size of the pie.",
                        "type": {
                            "integer": true
                        }
                    },
                    "gauge": {
                        "displayName": "Enable Gauge",
                        "description": "Display half of the chart as a gauge",
                        "type": {
                            "bool": true
                        }
                    },
                    "theme3d": {
                        "displayName": "Enable 3D",
                        "description": "Apply a 3D effect on the chart",
                        "type": {
                            "bool": true
                        }
                    },
                    "others": {
                        "displayName": "Enable `Others`",
                        "description": "Enable the `Others` and `Previous` slices",
                        "type": {
                            "bool": true
                        }
                    },
                    "maxSlicesVisible": {
                        "displayName": "Number Of Slices",
                        "description": "Number of visible slices before `Others` and `Previous` slices appear",
                        "type": {
                            "integer": true
                        }
                    },
                    "othersLabel": {
                        "displayName": "`Others` Label",
                        "description": "This setting allows to change the name of `Others` slice.",
                        "type": {
                            "text": true
                        }
                    },
                    "previousLabel": {
                        "displayName": "`Previous` Label",
                        "description": "This setting allows to change the name of `Previous` slice.",
                        "type": {
                            "text": true
                        }
                    },
                    "dataSorting": {
                        "displayName": "Data Sorting",
                        "type": {
                            "enumeration": [
                                {
                                    "value": "descending",
                                    "displayName": "Descending"
                                },
                                {
                                    "value": "ascending",
                                    "displayName": "Ascending"
                                },
                                {
                                    "value": "auto",
                                    "displayName": "Power BI built-in"
                                }
                            ]
                        }
                    },
                    "dataSortingBy": {
                        "displayName": "Data Sorting By",
                        "type": {
                            "enumeration": [
                                {
                                    "value": "name",
                                    "displayName": "Name"
                                },
                                {
                                    "value": "value",
                                    "displayName": "Value"
                                }
                            ]
                        }
                    },
                    "othersSizing": {
                        "displayName": "`Others`/`Previous` Sizing",
                        "description": "This setting allows to switch between actual and default sizing mode for the `Others` and `Previous` slices.",
                        "type": {
                            "enumeration": [
                                {
                                    "value": "default",
                                    "displayName": "Default"
                                },
                                {
                                    "value": "actual",
                                    "displayName": "Actual"
                                }
                            ]
                        }
                    },
                    "drillThroughToSingleSlice": {
                        "displayName": "Auto-Drill into Single Slices",
                        "type": {
                            "bool": true
                        }
                    },
                    "hideEmptyValues": {
                        "displayName": "Exclude Blank Categories",
                        "description": "Exclude categories that have blank names.",
                        "type": {
                            "bool": true
                        }
                    }
                }
            },
            "legend": {
                "displayName": "Legend",
                "properties": {
                    "show": {
                        "displayName": "Show",
                        "type": {
                            "bool": true
                        }
                    },
                    "displayMode": {
                        "displayName": "Display Mode",
                        "type": {
                            "enumeration": [
                                {
                                    "displayName": "Grid",
                                    "value": "grid"
                                },
                                {
                                    "displayName": "Inline",
                                    "value": "inline"
                                }
                            ]
                        }
                    },
                    "position": {
                        "displayName": "Position",
                        "type": {
                            "enumeration": [
                                {
                                    "value": "left",
                                    "displayName": "Left"
                                },
                                {
                                    "value": "right",
                                    "displayName": "Right"
                                },
                                {
                                    "value": "top",
                                    "displayName": "Top"
                                },
                                {
                                    "value": "bottom",
                                    "displayName": "Bottom"
                                }
                            ]
                        }
                    },
                    "alignHorizontal": {
                        "displayName": "Alignment",
                        "type": {
                            "enumeration": [
                                {
                                    "value": "left",
                                    "displayName": "Left"
                                },
                                {
                                    "value": "center",
                                    "displayName": "Center"
                                },
                                {
                                    "value": "right",
                                    "displayName": "Right"
                                }
                            ]
                        }
                    },
                    "alignVertical": {
                        "displayName": "Alignment",
                        "type": {
                            "enumeration": [
                                {
                                    "value": "top",
                                    "displayName": "Top"
                                },
                                {
                                    "value": "center",
                                    "displayName": "Middle"
                                },
                                {
                                    "value": "bottom",
                                    "displayName": "Bottom"
                                }
                            ]
                        }
                    },
                    "width": {
                        "displayName": "Width",
                        "description": "Control the desired width of the legend. 0 means auto. Legend width cannot be smaller than the space that it needs to render one item.",
                        "type": {
                            "integer": true
                        }
                    },
                    "height": {
                        "displayName": "Height",
                        "description": "Control the desired height of the legend. 0 means auto. Legend height cannot be smaller than the space that it needs to render one item.",
                        "type": {
                            "integer": true
                        }
                    },
                    "floating": {
                        "displayName": "Floating",
                        "description": "This setting lets you float the legend panel on top of the chart. This might be useful in cases where you have little space available. Note, that if enabled, chart may overlap with the legend entries.",
                        "type": {
                            "bool": true
                        }
                    },
                    "markerSize": {
                        "displayName": "Marker Size",
                        "type": {
                            "integer": true
                        }
                    },
                    "markerShape": {
                        "displayName": "Marker Shape",
                        "type": {
                            "enumeration": [
                                {
                                    "value": "circle",
                                    "displayName": "Circle"
                                },
                                {
                                    "value": "square",
                                    "displayName": "Square"
                                },
                                {
                                    "value": "rhombus",
                                    "displayName": "Rhombus"
                                },
                                {
                                    "value": "triangle",
                                    "displayName": "Triangle"
                                },
                                {
                                    "value": "triangle2",
                                    "displayName": "Triangle (upside down)"
                                }
                            ]
                        }
                    },
                    "fontSize": {
                        "displayName": "Font Size",
                        "description": "Font Size can be in px or pt, depending on the setting selected in Advanced Settings -> Font Size Unit.",
                        "type": {
                            "integer": true
                        }
                    },
                    "fontFamily": {
                        "displayName": "Font Family",
                        "type": {
                            "text": true
                        }
                    },
                    "fontStyle": {
                        "displayName": "Font Style",
                        "type": {
                            "enumeration": [
                                {
                                    "value": "",
                                    "displayName": "Regular"
                                },
                                {
                                    "value": "bold",
                                    "displayName": "Bold"
                                },
                                {
                                    "value": "italic",
                                    "displayName": "Italic"
                                },
                                {
                                    "value": "bold italic",
                                    "displayName": "Bold and italic"
                                }
                            ]
                        }
                    },
                    "fontColor": {
                        "displayName": "Font Color",
                        "type": {
                            "fill": {
                                "solid": {
                                    "color": true
                                }
                            }
                        }
                    },
                    "labelMode": {
                        "displayName": "Legend Label Style",
                        "type": {
                            "enumeration": [
                                {
                                    "value": "name",
                                    "displayName": "Category"
                                },
                                {
                                    "value": "value",
                                    "displayName": "Data value"
                                },
                                {
                                    "value": "perc",
                                    "displayName": "Percent of total"
                                },
                                {
                                    "value": "name+value",
                                    "displayName": "Category, data value"
                                },
                                {
                                    "value": "name+perc",
                                    "displayName": "Category, percent of total"
                                },
                                {
                                    "value": "value+perc",
                                    "displayName": "Data value, percent of total"
                                },
                                {
                                    "value": "name+value+perc",
                                    "displayName": "All detail labels"
                                }
                            ]
                        }
                    },
                    "allowZeroValues": {
                        "displayName": "Show Items With Zero Value",
                        "type": {
                            "bool": true
                        }
                    }
                }
            },
            "labels": {
                "displayName": "Detail Labels",
                "properties": {
                    "show": {
                        "displayName": "Show",
                        "type": {
                            "bool": true
                        }
                    },
                    "colorInside": {
                        "displayName": "Font Color",
                        "type": {
                            "fill": {
                                "solid": {
                                    "color": true
                                }
                            }
                        }
                    },
                    "colorOutside": {
                        "displayName": "Font Color",
                        "type": {
                            "fill": {
                                "solid": {
                                    "color": true
                                }
                            }
                        }
                    },
                    "mode": {
                        "displayName": "Label Style",
                        "type": {
                            "enumeration": [
                                {
                                    "value": "name",
                                    "displayName": "Category"
                                },
                                {
                                    "value": "value",
                                    "displayName": "Data value"
                                },
                                {
                                    "value": "perc",
                                    "displayName": "Percent of total"
                                },
                                {
                                    "value": "name+value",
                                    "displayName": "Category, data value"
                                },
                                {
                                    "value": "name+perc",
                                    "displayName": "Category, percent of total"
                                },
                                {
                                    "value": "value+perc",
                                    "displayName": "Data value, percent of total"
                                },
                                {
                                    "value": "name+value+perc",
                                    "displayName": "All detail labels"
                                }
                            ]
                        }
                    },
                    "placement": {
                        "displayName": "Label Placement",
                        "type": {
                            "enumeration": [
                                {
                                    "value": "inside",
                                    "displayName": "Inside"
                                },
                                {
                                    "value": "outside",
                                    "displayName": "Outside"
                                }
                            ]
                        }
                    },
                    "placementMode": {
                        "displayName": "Placement Mode",
                        "description": "Select the preferred label placement mode. 'Align' aligns labels in columns, 'Wrap' places them tightly around the chart.",
                        "type": {
                            "enumeration": [
                                {
                                    "value": "aligned",
                                    "displayName": "Align"
                                },
                                {
                                    "value": "wrap",
                                    "displayName": "Wrap"
                                }
                            ]
                        }
                    },
                    "fontSize": {
                        "displayName": "Font Size",
                        "description": "Font Size can be in px or pt, depending on the setting selected in Advanced Settings -> Font Size Unit.",
                        "type": {
                            "integer": true
                        }
                    },
                    "fontFamily": {
                        "displayName": "Font Family",
                        "type": {
                            "text": true
                        }
                    },
                    "fontStyle": {
                        "displayName": "Font Style",
                        "type": {
                            "enumeration": [
                                {
                                    "value": "",
                                    "displayName": "Regular"
                                },
                                {
                                    "value": "bold",
                                    "displayName": "Bold"
                                },
                                {
                                    "value": "italic",
                                    "displayName": "Italic"
                                },
                                {
                                    "value": "bold italic",
                                    "displayName": "Bold and italic"
                                }
                            ]
                        }
                    },
                    "displayUnits": {
                        "displayName": "Display Units",
                        "description": "Select the units (millions, billions, etc.)",
                        "type": {
                            "enumeration": [
                                {
                                    "value": "auto",
                                    "displayName": "Auto"
                                },
                                {
                                    "value": "",
                                    "displayName": "None"
                                },
                                {
                                    "value": "K",
                                    "displayName": "Thousands"
                                },
                                {
                                    "value": "M",
                                    "displayName": "Millions"
                                },
                                {
                                    "value": "bn",
                                    "displayName": "Billions"
                                },
                                {
                                    "value": "T",
                                    "displayName": "Trillions"
                                }
                            ]
                        }
                    },
                    "decimals": {
                        "displayName": "Value Decimals",
                        "description": "Set number of decimals for values",
                        "type": {
                            "enumeration": [
                                {
                                    "value": "auto",
                                    "displayName": "Auto"
                                },
                                {
                                    "value": "0",
                                    "displayName": "0"
                                },
                                {
                                    "value": "1",
                                    "displayName": "1"
                                },
                                {
                                    "value": "2",
                                    "displayName": "2"
                                },
                                {
                                    "value": "3",
                                    "displayName": "3"
                                },
                                {
                                    "value": "4",
                                    "displayName": "4"
                                },
                                {
                                    "value": "5",
                                    "displayName": "5"
                                },
                                {
                                    "value": "6",
                                    "displayName": "6"
                                },
                                {
                                    "value": "7",
                                    "displayName": "7"
                                },
                                {
                                    "value": "8",
                                    "displayName": "8"
                                },
                                {
                                    "value": "9",
                                    "displayName": "9"
                                }
                            ]
                        }
                    },
                    "decimalsPercentage": {
                        "displayName": "Percentage Decimals",
                        "description": "Set number of decimals for percents",
                        "type": {
                            "enumeration": [
                                {
                                    "value": "auto",
                                    "displayName": "Auto"
                                },
                                {
                                    "value": "0",
                                    "displayName": "0"
                                },
                                {
                                    "value": "1",
                                    "displayName": "1"
                                },
                                {
                                    "value": "2",
                                    "displayName": "2"
                                },
                                {
                                    "value": "3",
                                    "displayName": "3"
                                },
                                {
                                    "value": "4",
                                    "displayName": "4"
                                },
                                {
                                    "value": "5",
                                    "displayName": "5"
                                },
                                {
                                    "value": "6",
                                    "displayName": "6"
                                },
                                {
                                    "value": "7",
                                    "displayName": "7"
                                },
                                {
                                    "value": "8",
                                    "displayName": "8"
                                },
                                {
                                    "value": "9",
                                    "displayName": "9"
                                }
                            ]
                        }
                    },
                    "connectorColor": {
                        "displayName": "Connector Color",
                        "type": {
                            "fill": {
                                "solid": {
                                    "color": true
                                }
                            }
                        }
                    },
                    "connectorLength": {
                        "displayName": "Connector Length",
                        "description": "Length of connector",
                        "type": {
                            "integer": true
                        }
                    },
                    "connectorWidth": {
                        "displayName": "Connector Width (Thickness)",
                        "description": "Width of connector",
                        "type": {
                            "integer": true
                        }
                    }
                }
            },
            "popup": {
                "displayName": "Tooltip Settings",
                "properties": {
                    "show": {
                        "displayName": "Show",
                        "type": {
                            "bool": true
                        }
                    },
                    "tooltipType": {
                        "displayName": "Tooltip Type",
                        "description": "",
                        "type": {
                            "enumeration": [
                                {
                                    "value": "default_tooltip",
                                    "displayName": "Custom Tooltip"
                                },
                                {
                                    "value": "powerbi_tooltip",
                                    "displayName": "Power BI Tooltip"
                                }
                            ]
                        }
                    },
                    "displayUnits": {
                        "displayName": "Display Units",
                        "description": "Select the units (millions, billions, etc.)",
                        "type": {
                            "enumeration": [
                                {
                                    "value": "auto",
                                    "displayName": "Auto"
                                },
                                {
                                    "value": "",
                                    "displayName": "None"
                                },
                                {
                                    "value": "K",
                                    "displayName": "Thousands"
                                },
                                {
                                    "value": "M",
                                    "displayName": "Millions"
                                },
                                {
                                    "value": "bn",
                                    "displayName": "Billions"
                                },
                                {
                                    "value": "T",
                                    "displayName": "Trillions"
                                }
                            ]
                        }
                    },
                    "decimals": {
                        "displayName": "Value Decimals",
                        "description": "Set number of decimals",
                        "type": {
                            "enumeration": [
                                {
                                    "value": "auto",
                                    "displayName": "Auto"
                                },
                                {
                                    "value": "0",
                                    "displayName": "0"
                                },
                                {
                                    "value": "1",
                                    "displayName": "1"
                                },
                                {
                                    "value": "2",
                                    "displayName": "2"
                                },
                                {
                                    "value": "3",
                                    "displayName": "3"
                                },
                                {
                                    "value": "4",
                                    "displayName": "4"
                                },
                                {
                                    "value": "5",
                                    "displayName": "5"
                                },
                                {
                                    "value": "6",
                                    "displayName": "6"
                                },
                                {
                                    "value": "7",
                                    "displayName": "7"
                                },
                                {
                                    "value": "8",
                                    "displayName": "8"
                                },
                                {
                                    "value": "9",
                                    "displayName": "9"
                                }
                            ]
                        }
                    },
                    "decimalsPercentage": {
                        "displayName": "Percentage Decimals",
                        "description": "Set number of decimals for percents",
                        "type": {
                            "enumeration": [
                                {
                                    "value": "auto",
                                    "displayName": "Auto"
                                },
                                {
                                    "value": "0",
                                    "displayName": "0"
                                },
                                {
                                    "value": "1",
                                    "displayName": "1"
                                },
                                {
                                    "value": "2",
                                    "displayName": "2"
                                },
                                {
                                    "value": "3",
                                    "displayName": "3"
                                },
                                {
                                    "value": "4",
                                    "displayName": "4"
                                },
                                {
                                    "value": "5",
                                    "displayName": "5"
                                },
                                {
                                    "value": "6",
                                    "displayName": "6"
                                },
                                {
                                    "value": "7",
                                    "displayName": "7"
                                },
                                {
                                    "value": "8",
                                    "displayName": "8"
                                },
                                {
                                    "value": "9",
                                    "displayName": "9"
                                }
                            ]
                        }
                    }
                }
            },
            "toolbar": {
                "displayName": "Toolbar",
                "properties": {
                    "show": {
                        "displayName": "Show",
                        "type": {
                            "bool": true
                        }
                    },
                    "zoomOutBtn": {
                        "displayName": "Zoom Out Button",
                        "description": "Whether to show the `Zoom Out` button in the toolbar",
                        "type": {
                            "bool": true
                        }
                    },
                    "backBtn": {
                        "displayName": "Back Button",
                        "description": "Whether to show the `Back` button in the toolbar",
                        "type": {
                            "bool": true
                        }
                    },
                    "darkMode": {
                        "displayName": "Dark Mode",
                        "description": "Dark mode",
                        "type": {
                            "bool": true
                        }
                    },
                    "resetBtn": {
                        "displayName": "Reset Button",
                        "description": "Resets visual to initial state",
                        "type": {
                            "bool": true
                        }
                    },
                    "location": {
                        "displayName": "Location of the toolbar",
                        "description": "Toolbar can be shown on the chart area our outside it",
                        "type": {
                            "enumeration": [
                                {
                                    "value": "inside",
                                    "displayName": "Inside"
                                },
                                {
                                    "value": "outside",
                                    "displayName": "Outside"
                                }
                            ]
                        }
                    }
                }
            },
            "fillSettings": {
                "displayName": "Fill Color Settings",
                "properties": {
                    "gradient": {
                        "displayName": "Fill Mode",
                        "type": {
                            "enumeration": [
                                {
                                    "value": "solid",
                                    "displayName": "Solid fill"
                                },
                                {
                                    "value": "derived",
                                    "displayName": "Gradient to a derived color"
                                },
                                {
                                    "value": "gradient",
                                    "displayName": "Gradient to a single color"
                                }
                            ]
                        }
                    },
                    "baseFillColor": {
                        "displayName": "Base Fill Color",
                        "type": {
                            "fill": {
                                "solid": {
                                    "color": true
                                }
                            }
                        }
                    },
                    "gradientColor": {
                        "displayName": "Gradient Color",
                        "type": {
                            "fill": {
                                "solid": {
                                    "color": true
                                }
                            }
                        }
                    },
                    "opacity": {
                        "displayName": "Slice Outer Opacity",
                        "description": "Opacity of the gradient color, 0 - transparent, 100 - opaque. This setting controls the outermost opacity level of the slice, if gradient mode is enabled. Opacity starts from 100 at the Gradient start location and decreases towards the set value in a linear way.",
                        "type": {
                            "integer": true
                        }
                    },
                    "gradientStep": {
                        "displayName": "Gradient Start Location",
                        "description": "0 - inside, 100 - outside. If the outer opacity of the slice is provided, opacity calculation starts at this point from 100 to the specified opacity value.",
                        "type": {
                            "integer": true
                        }
                    },
                    "baseColorHueAdjustment": {
                        "displayName": "Hue Adjustment",
                        "description": "50 - no Adjustment. 0 - 0 hue, 100 - 100 hue",
                        "type": {
                            "integer": true
                        }
                    },
                    "baseColorSaturationAdjustment": {
                        "displayName": "Saturation Adjustment",
                        "description": "0 means 0% saturation, 100 means 100% saturation;  50 means saturation is unaffected. E.g. 51 means that additional 1% is added to the color's saturation.",
                        "type": {
                            "integer": true
                        }
                    },
                    "baseColorLightnessAdjustment": {
                        "displayName": "Lightness Adjustment",
                        "description": "0 means 0% lightness, 100 means 100% lightness;  50 means lightness is unaffected. E.g. 51 means that additional 1% is added to the color's lightness.",
                        "type": {
                            "integer": true
                        }
                    }
                }
            },
            "colors1": {
                "displayName": "Category 1 Colors",
                "properties": {
                    "fill": {
                        "displayName": "Color",
                        "type": {
                            "fill": {
                                "solid": {
                                    "color": true
                                }
                            }
                        }
                    }
                }
            },
            "colors2": {
                "displayName": "Category 2 Colors",
                "properties": {
                    "fill": {
                        "displayName": "Color",
                        "type": {
                            "fill": {
                                "solid": {
                                    "color": true
                                }
                            }
                        }
                    }
                }
            },
            "colors3": {
                "displayName": "Category 3 Colors",
                "properties": {
                    "fill": {
                        "displayName": "Color",
                        "type": {
                            "fill": {
                                "solid": {
                                    "color": true
                                }
                            }
                        }
                    }
                }
            },
            "colors4": {
                "displayName": "Category 4 Colors",
                "properties": {
                    "fill": {
                        "displayName": "Color",
                        "type": {
                            "fill": {
                                "solid": {
                                    "color": true
                                }
                            }
                        }
                    }
                }
            },
            "colors5": {
                "displayName": "Category 5 Colors",
                "properties": {
                    "fill": {
                        "displayName": "Color",
                        "type": {
                            "fill": {
                                "solid": {
                                    "color": true
                                }
                            }
                        }
                    }
                }
            },
            "colors6": {
                "displayName": "Category 6 Colors",
                "properties": {
                    "fill": {
                        "displayName": "Color",
                        "type": {
                            "fill": {
                                "solid": {
                                    "color": true
                                }
                            }
                        }
                    }
                }
            },
            "colors7": {
                "displayName": "Category 7 Colors",
                "properties": {
                    "fill": {
                        "displayName": "Color",
                        "type": {
                            "fill": {
                                "solid": {
                                    "color": true
                                }
                            }
                        }
                    }
                }
            },
            "colors8": {
                "displayName": "Category 8 Colors",
                "properties": {
                    "fill": {
                        "displayName": "Color",
                        "type": {
                            "fill": {
                                "solid": {
                                    "color": true
                                }
                            }
                        }
                    }
                }
            },
            "colors9": {
                "displayName": "Category 9 Colors",
                "properties": {
                    "fill": {
                        "displayName": "Color",
                        "type": {
                            "fill": {
                                "solid": {
                                    "color": true
                                }
                            }
                        }
                    }
                }
            }
        }
    },
    "visualEntryPoint": "",
    "externalJS": [],
    "assets": {
        "icon": "assets/icon.png"
    }
}