{
    "visual": {
        "name": "Vistogram",
        "displayName": "Vistogram\u00ae from Omnivisto\u00ae",
        "guid": "vistogram0B398B567E3F4F139426071FD4BB8BC5",
        "visualClassName": "Visual",
        "version": "1.0.0.25",
        "description": "Keep the big picture in view with Vistogram\u00ae from Omnivisto\u00ae.",
        "supportUrl": "omnivisto.com",
        "gitHubUrl": ""
    },
    "author": {
        "name": "Omnivisto\u00ae",
        "email": "support@omnivisto.co.uk"
    },
    "apiVersion": "5.11.0",
    "style": "style/visual.less",
    "stringResources": {},
    "capabilities": {
        "dataRoles": [
            {
                "name": "id",
                "kind": "Grouping",
                "displayName": "ID"
            },
            {
                "name": "outlineNumber",
                "kind": "Grouping",
                "displayName": "Outline"
            },
            {
                "name": "name",
                "kind": "Grouping",
                "displayName": "Name",
                "preferredTypes": [
                    {
                        "text": true
                    }
                ]
            },
            {
                "name": "startDate",
                "kind": "Grouping",
                "displayName": "Start Date"
            },
            {
                "name": "endDate",
                "kind": "Grouping",
                "displayName": "End Date"
            },
            {
                "name": "rag",
                "kind": "Grouping",
                "displayName": "RAG (Optional)"
            },
            {
                "name": "%complete",
                "kind": "Grouping",
                "displayName": "% Complete (Optional)"
            }
        ],
        "dataViewMappings": [
            {
                "table": {
                    "rows": {
                        "dataReductionAlgorithm": {
                            "window": {
                                "count": 30000
                            }
                        },
                        "select": [
                            {
                                "for": {
                                    "in": "id"
                                }
                            },
                            {
                                "for": {
                                    "in": "outlineNumber"
                                }
                            },
                            {
                                "for": {
                                    "in": "name"
                                }
                            },
                            {
                                "for": {
                                    "in": "startDate"
                                }
                            },
                            {
                                "for": {
                                    "in": "endDate"
                                }
                            },
                            {
                                "for": {
                                    "in": "rag"
                                }
                            },
                            {
                                "for": {
                                    "in": "%complete"
                                }
                            }
                        ]
                    }
                }
            }
        ],
        "objects": {
            "general": {
                "displayName": "General",
                "displayNameKey": "formattingGeneral",
                "properties": {
                    "filter": {
                        "type": {
                            "filter": true
                        }
                    }
                }
            },
            "vistogramCard": {
                "properties": {
                    "generalFontOptions": {
                        "type": {
                            "enumeration": []
                        }
                    },
                    "autoScaledFontSwitch": {
                        "type": {
                            "bool": true
                        }
                    },
                    "arcLightSwitch": {
                        "type": {
                            "bool": true
                        }
                    },
                    "popupsFontSwitch": {
                        "type": {
                            "bool": true
                        }
                    }
                }
            },
            "layoutCard": {
                "properties": {
                    "orientationChoice": {
                        "type": {
                            "enumeration": []
                        }
                    },
                    "coordinatesChoice": {
                        "type": {
                            "enumeration": []
                        }
                    },
                    "tiersNumUpDown": {
                        "type": {
                            "numeric": true
                        }
                    },
                    "startingAngleNumUpDown": {
                        "type": {
                            "numeric": true
                        }
                    }
                }
            },
            "activitiesCard": {
                "properties": {
                    "activitiesBorderColour": {
                        "type": {
                            "fill": {
                                "solid": {
                                    "color": true
                                }
                            }
                        }
                    },
                    "activitiesBorderWidthNumUpDown": {
                        "type": {
                            "numeric": true
                        }
                    },
                    "activitiesFontSizeNumUpDown": {
                        "type": {
                            "numeric": true
                        }
                    },
                    "activitiesFontColourColorPicker": {
                        "type": {
                            "fill": {
                                "solid": {
                                    "color": true
                                }
                            }
                        }
                    },
                    "activitiesFillColourColorPicker": {
                        "type": {
                            "fill": {
                                "solid": {
                                    "color": true
                                }
                            }
                        }
                    },
                    "activitiesBoldSwitch": {
                        "type": {
                            "bool": true
                        }
                    }
                }
            },
            "timelineCard": {
                "properties": {
                    "timelineBorderColourColorPicker": {
                        "type": {
                            "fill": {
                                "solid": {
                                    "color": true
                                }
                            }
                        }
                    },
                    "timelineBorderWidthNumUpDown": {
                        "type": {
                            "numeric": true
                        }
                    },
                    "timelineFillStyleChoice": {
                        "type": {
                            "enumeration": []
                        }
                    },
                    "timelineFillPrimaryColorPicker": {
                        "type": {
                            "fill": {
                                "solid": {
                                    "color": true
                                }
                            }
                        }
                    },
                    "timelineFillSecondaryColorPicker": {
                        "type": {
                            "fill": {
                                "solid": {
                                    "color": true
                                }
                            }
                        }
                    },
                    "timelineFontSizeNumUpDown": {
                        "type": {
                            "numeric": true
                        }
                    },
                    "timelineFontColorPicker": {
                        "type": {
                            "fill": {
                                "solid": {
                                    "color": true
                                }
                            }
                        }
                    },
                    "timelineFontBoldToggle": {
                        "type": {
                            "bool": true
                        }
                    },
                    "timelineTodayCardShow": {
                        "type": {
                            "bool": true
                        }
                    },
                    "timelineTodayColourColorPicker": {
                        "type": {
                            "fill": {
                                "solid": {
                                    "color": true
                                }
                            }
                        }
                    }
                }
            },
            "backgroundCard": {
                "properties": {
                    "backgroundFillColourColorPicker": {
                        "type": {
                            "fill": {
                                "solid": {
                                    "color": true
                                }
                            }
                        }
                    }
                }
            },
            "gridlinesCard": {
                "properties": {
                    "gridlinesColourColorPicker": {
                        "type": {
                            "fill": {
                                "solid": {
                                    "color": true
                                }
                            }
                        }
                    },
                    "gridlinesBorderWidthNumUpDown": {
                        "type": {
                            "numeric": true
                        }
                    },
                    "gridlinesHorizontalToggle": {
                        "type": {
                            "bool": true
                        }
                    },
                    "gridlinesVerticalMajorToggle": {
                        "type": {
                            "bool": true
                        }
                    },
                    "gridlinesVerticalMinorToggle": {
                        "type": {
                            "bool": true
                        }
                    }
                }
            },
            "milestonesCard": {
                "properties": {
                    "milestonesBorderColour": {
                        "type": {
                            "fill": {
                                "solid": {
                                    "color": true
                                }
                            }
                        }
                    },
                    "milestonesBorderWidthNumUpDown": {
                        "type": {
                            "numeric": true
                        }
                    },
                    "milestonesFontSizeNumUpDown": {
                        "type": {
                            "numeric": true
                        }
                    },
                    "milestonesFontColourColorPicker": {
                        "type": {
                            "fill": {
                                "solid": {
                                    "color": true
                                }
                            }
                        }
                    },
                    "milestonesFontBoldToggle": {
                        "type": {
                            "bool": true
                        }
                    },
                    "milestonesShapeFillColourColorPicker": {
                        "type": {
                            "fill": {
                                "solid": {
                                    "color": true
                                }
                            }
                        }
                    },
                    "milestonesShapeChoice": {
                        "type": {
                            "enumeration": []
                        }
                    }
                }
            }
        },
        "privileges": []
    },
    "visualEntryPoint": "",
    "externalJS": [],
    "assets": {
        "icon": "assets/icon.png"
    }
}